[{"keyword":"Feature","type":"feature","description":"","line":2,"name":"Login","uri":"D:\\Documents\\QA Engineering Digital Skola\\wdio-pom-ds5\\features\\login.feature","tags":[{"location":{"line":1,"column":1},"name":"@login","id":"2ed5b710-001b-4a8c-b9a9-19bcbf2deb32"}],"elements":[{"keyword":"Scenario","type":"scenario","description":"","name":"As a user, I can log into home page","tags":[{"name":"@login","astNodeId":"2ed5b710-001b-4a8c-b9a9-19bcbf2deb32"},{"name":"@positive","astNodeId":"6d9fdbc6-248f-4153-9ddd-d54a8e70bdb3"}],"id":"loginas-a-user,-i-can-log-into-home-page","steps":[{"arguments":[],"keyword":"Before","name":"","result":{"status":"passed","duration":5000000},"line":null,"match":{"location":"can not be determined with webdriver.io"}},{"arguments":[],"keyword":"Given","name":"I am on the login page","result":{"status":"passed","duration":583000000},"line":null,"match":{"location":"can not be determined with webdriver.io"}},{"arguments":[],"keyword":"When","name":"I login with standard_user and secret_sauce","result":{"status":"passed","duration":582000000},"line":null,"match":{"location":"can not be determined with webdriver.io"}},{"arguments":[],"keyword":"Then","name":"I should redirected to home page","result":{"status":"passed","duration":99000000},"line":null,"match":{"location":"can not be determined with webdriver.io"}},{"arguments":[],"keyword":"After","name":"","result":{"status":"passed","duration":1000000},"line":null,"match":{"location":"can not be determined with webdriver.io"}}]},{"keyword":"Scenario","type":"scenario","description":"","name":"As a user, I can log into home page","tags":[{"name":"@login","astNodeId":"2ed5b710-001b-4a8c-b9a9-19bcbf2deb32"},{"name":"@positive","astNodeId":"6d9fdbc6-248f-4153-9ddd-d54a8e70bdb3"}],"id":"loginas-a-user,-i-can-log-into-home-page","steps":[{"arguments":[],"keyword":"Before","name":"","result":{"status":"passed","duration":1000000},"line":null,"match":{"location":"can not be determined with webdriver.io"}},{"arguments":[],"keyword":"Given","name":"I am on the login page","result":{"status":"passed","duration":108000000},"line":null,"match":{"location":"can not be determined with webdriver.io"}},{"arguments":[],"keyword":"When","name":"I login with visual_user and secret_sauce","result":{"status":"passed","duration":490000000},"line":null,"match":{"location":"can not be determined with webdriver.io"}},{"arguments":[],"keyword":"Then","name":"I should redirected to home page","result":{"status":"passed","duration":213000000},"line":null,"match":{"location":"can not be determined with webdriver.io"}},{"arguments":[],"keyword":"After","name":"","result":{"status":"passed","duration":2000000},"line":null,"match":{"location":"can not be determined with webdriver.io"}}]},{"keyword":"Scenario","type":"scenario","description":"","name":"Log in with invalid credentials","tags":[{"name":"@login","astNodeId":"2ed5b710-001b-4a8c-b9a9-19bcbf2deb32"},{"name":"@negative","astNodeId":"6a3b7294-b59b-4e3f-abc7-2708960b4063"}],"id":"loginlog-in-with-invalid-credentials","steps":[{"arguments":[],"keyword":"Before","name":"","result":{"status":"passed","duration":1000000},"line":null,"match":{"location":"can not be determined with webdriver.io"}},{"arguments":[],"keyword":"Given","name":"I am on the login page","result":{"status":"passed","duration":71000000},"line":null,"match":{"location":"can not be determined with webdriver.io"}},{"arguments":[],"keyword":"When","name":"I login with stasdsda_user and lalalalalaal","result":{"status":"passed","duration":404000000},"line":null,"match":{"location":"can not be determined with webdriver.io"}},{"arguments":[],"keyword":"Then","name":"I should see an error message Epic sadface: Username and password do not match any user in this service","result":{"status":"failed","duration":2000000,"error_message":"Step \"I should see an error message Epic sadface: Username and password do not match any user in this service\" is not defined. You can ignore this error by setting cucumberOpts.ignoreUndefinedDefinitions as true.\n\tat Feature(D:\\Documents\\QA Engineering Digital Skola\\wdio-pom-ds5\\features\\login.feature):1:1\n\tat Scenario(Log in with invalid credentials):19:3\n\tat Step(I should see an error message <errorMessage>):22:5\n"},"line":null,"match":{"location":"can not be determined with webdriver.io"}},{"arguments":[],"keyword":"After","name":"","result":{"status":"passed","duration":1000000},"line":null,"match":{"location":"can not be determined with webdriver.io"}}]},{"keyword":"Scenario","type":"scenario","description":"","name":"Log in with invalid credentials","tags":[{"name":"@login","astNodeId":"2ed5b710-001b-4a8c-b9a9-19bcbf2deb32"},{"name":"@negative","astNodeId":"6a3b7294-b59b-4e3f-abc7-2708960b4063"}],"id":"loginlog-in-with-invalid-credentials","steps":[{"arguments":[],"keyword":"Before","name":"","result":{"status":"passed","duration":1000000},"line":null,"match":{"location":"can not be determined with webdriver.io"}},{"arguments":[],"keyword":"Given","name":"I am on the login page","result":{"status":"passed","duration":70000000},"line":null,"match":{"location":"can not be determined with webdriver.io"}},{"arguments":[],"keyword":"When","name":"I login with standard_user and","result":{"status":"failed","duration":1000000,"error_message":"Step \"I login with standard_user and \" is not defined. You can ignore this error by setting cucumberOpts.ignoreUndefinedDefinitions as true.\n\tat Feature(D:\\Documents\\QA Engineering Digital Skola\\wdio-pom-ds5\\features\\login.feature):1:1\n\tat Scenario(Log in with invalid credentials):19:3\n\tat Step(I login with <username> and <password>):21:5\n"},"line":null,"match":{"location":"can not be determined with webdriver.io"}},{"arguments":[],"keyword":"Then","name":"I should see an error message Epic sadface: Password is required","result":{"status":"failed","duration":1000000,"error_message":"Step \"I should see an error message Epic sadface: Password is required\" is not defined. You can ignore this error by setting cucumberOpts.ignoreUndefinedDefinitions as true.\n\tat Feature(D:\\Documents\\QA Engineering Digital Skola\\wdio-pom-ds5\\features\\login.feature):1:1\n\tat Scenario(Log in with invalid credentials):19:3\n\tat Step(I should see an error message <errorMessage>):22:5\n"},"line":null,"match":{"location":"can not be determined with webdriver.io"}},{"arguments":[],"keyword":"After","name":"","result":{"status":"passed","duration":1000000},"line":null,"match":{"location":"can not be determined with webdriver.io"}}]},{"keyword":"Scenario","type":"scenario","description":"","name":"Log in with invalid credentials","tags":[{"name":"@login","astNodeId":"2ed5b710-001b-4a8c-b9a9-19bcbf2deb32"},{"name":"@negative","astNodeId":"6a3b7294-b59b-4e3f-abc7-2708960b4063"}],"id":"loginlog-in-with-invalid-credentials","steps":[{"arguments":[],"keyword":"Before","name":"","result":{"status":"passed","duration":1000000},"line":null,"match":{"location":"can not be determined with webdriver.io"}},{"arguments":[],"keyword":"Given","name":"I am on the login page","result":{"status":"passed","duration":68000000},"line":null,"match":{"location":"can not be determined with webdriver.io"}},{"arguments":[],"keyword":"When","name":"I login with  and","result":{"status":"failed","duration":1000000,"error_message":"Step \"I login with  and \" is not defined. You can ignore this error by setting cucumberOpts.ignoreUndefinedDefinitions as true.\n\tat Feature(D:\\Documents\\QA Engineering Digital Skola\\wdio-pom-ds5\\features\\login.feature):1:1\n\tat Scenario(Log in with invalid credentials):19:3\n\tat Step(I login with <username> and <password>):21:5\n"},"line":null,"match":{"location":"can not be determined with webdriver.io"}},{"arguments":[],"keyword":"Then","name":"I should see an error message Epic sadface: Username is required","result":{"status":"failed","duration":1000000,"error_message":"Step \"I should see an error message Epic sadface: Username is required\" is not defined. You can ignore this error by setting cucumberOpts.ignoreUndefinedDefinitions as true.\n\tat Feature(D:\\Documents\\QA Engineering Digital Skola\\wdio-pom-ds5\\features\\login.feature):1:1\n\tat Scenario(Log in with invalid credentials):19:3\n\tat Step(I should see an error message <errorMessage>):22:5\n"},"line":null,"match":{"location":"can not be determined with webdriver.io"}},{"arguments":[],"keyword":"After","name":"","result":{"status":"passed","duration":1000000},"line":null,"match":{"location":"can not be determined with webdriver.io"}}]}],"id":"login","metadata":{"browser":{"name":"MicrosoftEdge","version":"128.0.2739.54"},"device":"Device name not known","platform":{"name":"windows","version":"Version not known"}}}]
